regressioninc/__init__.py
regressioninc/base.py
regressioninc/linear.py
regressioninc/testing/__init__.py
regressioninc/testing/complex.py
regressioninc/testing/real.py
regressioninc-0.1.0a0.dist-info/LICENSE
regressioninc-0.1.0a0.dist-info/METADATA
regressioninc-0.1.0a0.dist-info/WHEEL
regressioninc-0.1.0a0.dist-info/RECORD
